azampay/__init__.py
azampay/azampay_exceptions.py
azampay-0.3.dist-info/LICENSE
azampay-0.3.dist-info/METADATA
azampay-0.3.dist-info/WHEEL
azampay-0.3.dist-info/top_level.txt
azampay-0.3.dist-info/RECORD
