Metadata-Version: 2.1
Name: azampay
Version: 0.3
Summary: Opensource python wrapper for Azampay API
Home-page: https://github.com/Neurotech-HQ/azampay
Author: Jordan Kalebu
Author-email: isaackeinstein@gmail.com
License: MIT
Download-URL: https://github.com/Neurotech-HQ/azampay/archive/refs/tags/v0.1.tar.gz
Keywords: azampay,azampay SDK,Azam pay SDK,Azampay Wrapper,Payment Gateway Tanzania,tigopesa,mpesa,airtel money,halopesa
Platform: UNKNOWN
Classifier: Development Status :: 3 - Alpha
Classifier: Intended Audience :: Developers
Classifier: Topic :: Software Development :: Build Tools
Classifier: License :: OSI Approved :: MIT License
Classifier: Programming Language :: Python :: 3.6
Classifier: Programming Language :: Python :: 3.7
Classifier: Programming Language :: Python :: 3.8
Classifier: Programming Language :: Python :: 3.9
Classifier: Programming Language :: Python :: 3.10
Requires-Python: >=3.6
Requires-Dist: phonenumbers
Requires-Dist: requests
